[
    {
        "end": 14.461051177978515, 
        "index": 1, 
        "repeat": 0, 
        "start": 11.860464096069336, 
        "wavfile": "F002_002_01_0101"
    }, 
    {
        "end": 15.77479109764099, 
        "index": 2, 
        "repeat": 0, 
        "start": 14.036079072952273, 
        "wavfile": "F002_002_01_0101"
    }, 
    {
        "end": 17.5183319568634, 
        "index": 3, 
        "repeat": 0, 
        "start": 15.521734142303467, 
        "wavfile": "F002_002_01_0101"
    }, 
    {
        "end": 20.57932295799256, 
        "index": 4, 
        "repeat": 0, 
        "start": 17.421736145019523, 
        "wavfile": "F002_002_01_0101"
    }, 
    {
        "end": 25.301319980621336, 
        "index": 5, 
        "repeat": 0, 
        "start": 22.68217515945433, 
        "wavfile": "F002_002_01_0101"
    }, 
    {
        "end": 26.68610200881958, 
        "index": 6, 
        "repeat": 0, 
        "start": 25.052687072753898, 
        "wavfile": "F002_002_01_0101"
    }, 
    {
        "end": 28.26857595443726, 
        "index": 7, 
        "repeat": 0, 
        "start": 26.432770013809197, 
        "wavfile": "F002_002_01_0101"
    }, 
    {
        "end": 29.91056799888611, 
        "index": 8, 
        "repeat": 0, 
        "start": 27.98786497116088, 
        "wavfile": "F002_002_01_0101"
    }, 
    {
        "end": 33.182506084442146, 
        "index": 9, 
        "repeat": 0, 
        "start": 29.765122079849235, 
        "wavfile": "F002_002_01_0101"
    }, 
    {
        "end": 37.62153611183167, 
        "index": 10, 
        "repeat": 0, 
        "start": 34.95772705078124, 
        "wavfile": "F002_002_01_0101"
    }, 
    {
        "end": 40.71792402267456, 
        "index": 11, 
        "repeat": 0, 
        "start": 37.52275896072387, 
        "wavfile": "F002_002_01_0101"
    }, 
    {
        "end": 44.339712142944336, 
        "index": 12, 
        "repeat": 0, 
        "start": 40.663635015487664, 
        "wavfile": "F002_002_01_0101"
    }, 
    {
        "end": 49.70749111175537, 
        "index": 13, 
        "repeat": 0, 
        "start": 44.33560509681701, 
        "wavfile": "F002_002_01_0101"
    }, 
    {
        "end": 53.1424940109253, 
        "index": 14, 
        "repeat": 0, 
        "start": 49.513390016555775, 
        "wavfile": "F002_002_01_0101"
    }, 
    {
        "end": 55.71540398597717, 
        "index": 15, 
        "repeat": 0, 
        "start": 53.07624702453613, 
        "wavfile": "F002_002_01_0101"
    }, 
    {
        "end": 59.17611107826233, 
        "index": 16, 
        "repeat": 0, 
        "start": 55.53822197914123, 
        "wavfile": "F002_002_01_0101"
    }, 
    {
        "end": 62.054141998291016, 
        "index": 17, 
        "repeat": 0, 
        "start": 58.87899017333984, 
        "wavfile": "F002_002_01_0101"
    }, 
    {
        "end": 65.4060191631317, 
        "index": 18, 
        "repeat": 0, 
        "start": 61.78584098815917, 
        "wavfile": "F002_002_01_0101"
    }, 
    {
        "end": 68.08631916046144, 
        "index": 19, 
        "repeat": 0, 
        "start": 65.36952800750734, 
        "wavfile": "F002_002_01_0101"
    }, 
    {
        "end": 71.58092298507688, 
        "index": 20, 
        "repeat": 0, 
        "start": 67.88102512359623, 
        "wavfile": "F002_002_01_0101"
    }, 
    {
        "end": 76.54067311286914, 
        "index": 21, 
        "repeat": 0, 
        "start": 71.27295513153078, 
        "wavfile": "F002_002_01_0101"
    }, 
    {
        "end": 79.49934916496275, 
        "index": 22, 
        "repeat": 0, 
        "start": 77.59920902252202, 
        "wavfile": "F002_002_01_0101"
    }, 
    {
        "end": 80.87517504692076, 
        "index": 23, 
        "repeat": 0, 
        "start": 79.07940897941592, 
        "wavfile": "F002_002_01_0101"
    }, 
    {
        "end": 82.60602297782896, 
        "index": 24, 
        "repeat": 0, 
        "start": 80.65466008186343, 
        "wavfile": "F002_002_01_0101"
    }, 
    {
        "end": 85.95976104736326, 
        "index": 25, 
        "repeat": 0, 
        "start": 82.44588994979858, 
        "wavfile": "F002_002_01_0101"
    }, 
    {
        "end": 90.3032980442047, 
        "index": 26, 
        "repeat": 0, 
        "start": 87.92341313362127, 
        "wavfile": "F002_002_01_0101"
    }, 
    {
        "end": 91.65715618133544, 
        "index": 27, 
        "repeat": 0, 
        "start": 90.01966896057132, 
        "wavfile": "F002_002_01_0101"
    }, 
    {
        "end": 93.33570203781127, 
        "index": 28, 
        "repeat": 0, 
        "start": 91.6851791381836, 
        "wavfile": "F002_002_01_0101"
    }, 
    {
        "end": 94.96810407638549, 
        "index": 29, 
        "repeat": 0, 
        "start": 92.94362401962283, 
        "wavfile": "F002_002_01_0101"
    }, 
    {
        "end": 98.44461102485656, 
        "index": 30, 
        "repeat": 0, 
        "start": 94.82300505638125, 
        "wavfile": "F002_002_01_0101"
    }, 
    {
        "end": 102.80877304077148, 
        "index": 31, 
        "repeat": 0, 
        "start": 100.22667202949529, 
        "wavfile": "F002_002_01_0101"
    }, 
    {
        "end": 105.79311313629151, 
        "index": 32, 
        "repeat": 0, 
        "start": 102.60828409194949, 
        "wavfile": "F002_002_01_0101"
    }, 
    {
        "end": 109.25258617401121, 
        "index": 33, 
        "repeat": 0, 
        "start": 105.7043540477753, 
        "wavfile": "F002_002_01_0101"
    }, 
    {
        "end": 113.6273741722107, 
        "index": 34, 
        "repeat": 0, 
        "start": 109.3397550582886, 
        "wavfile": "F002_002_01_0101"
    }, 
    {
        "end": 118.1788261413574, 
        "index": 35, 
        "repeat": 0, 
        "start": 114.46567001342777, 
        "wavfile": "F002_002_01_0101"
    }, 
    {
        "end": 120.74698405265809, 
        "index": 36, 
        "repeat": 0, 
        "start": 118.03900508880616, 
        "wavfile": "F002_002_01_0101"
    }, 
    {
        "end": 124.19442200660706, 
        "index": 37, 
        "repeat": 0, 
        "start": 120.52122511863712, 
        "wavfile": "F002_002_01_0101"
    }, 
    {
        "end": 127.11165809631348, 
        "index": 38, 
        "repeat": 0, 
        "start": 124.04264397621156, 
        "wavfile": "F002_002_01_0101"
    }, 
    {
        "end": 130.59798908233643, 
        "index": 39, 
        "repeat": 0, 
        "start": 126.84415206909182, 
        "wavfile": "F002_002_01_0101"
    }, 
    {
        "end": 133.12069811820984, 
        "index": 40, 
        "repeat": 0, 
        "start": 130.5692800998688, 
        "wavfile": "F002_002_01_0101"
    }, 
    {
        "end": 136.62792301177979, 
        "index": 41, 
        "repeat": 0, 
        "start": 132.89241209030155, 
        "wavfile": "F002_002_01_0101"
    }, 
    {
        "end": 139.80849714279174, 
        "index": 42, 
        "repeat": 0, 
        "start": 136.360909986496, 
        "wavfile": "F002_002_01_0101"
    }, 
    {
        "end": 142.06838512420654, 
        "index": 43, 
        "repeat": 0, 
        "start": 140.82506608963013, 
        "wavfile": "F002_002_01_0101"
    }, 
    {
        "end": 155.4272271156311, 
        "index": 44, 
        "repeat": 0, 
        "start": 151.94100208282475, 
        "wavfile": "F002_002_01_0101"
    }, 
    {
        "end": 159.19815106391908, 
        "index": 45, 
        "repeat": 0, 
        "start": 155.2121231555939, 
        "wavfile": "F002_002_01_0101"
    }, 
    {
        "end": 162.4361979961395, 
        "index": 46, 
        "repeat": 0, 
        "start": 158.59178295135504, 
        "wavfile": "F002_002_01_0101"
    }, 
    {
        "end": 167.92639503479003, 
        "index": 47, 
        "repeat": 0, 
        "start": 163.80448007583624, 
        "wavfile": "F002_002_01_0101"
    }, 
    {
        "end": 170.32430200576783, 
        "index": 48, 
        "repeat": 0, 
        "start": 167.62685213088992, 
        "wavfile": "F002_002_01_0101"
    }, 
    {
        "end": 173.84394216537473, 
        "index": 49, 
        "repeat": 0, 
        "start": 170.29157004356387, 
        "wavfile": "F002_002_01_0101"
    }, 
    {
        "end": 176.77035999298096, 
        "index": 50, 
        "repeat": 0, 
        "start": 173.50636210441593, 
        "wavfile": "F002_002_01_0101"
    }, 
    {
        "end": 180.20151195526122, 
        "index": 51, 
        "repeat": 0, 
        "start": 176.7213739871979, 
        "wavfile": "F002_002_01_0101"
    }, 
    {
        "end": 182.7608759880066, 
        "index": 52, 
        "repeat": 0, 
        "start": 179.96188516616823, 
        "wavfile": "F002_002_01_0101"
    }, 
    {
        "end": 186.2091821193695, 
        "index": 53, 
        "repeat": 0, 
        "start": 182.61878108978274, 
        "wavfile": "F002_002_01_0101"
    }, 
    {
        "end": 189.30484199523926, 
        "index": 54, 
        "repeat": 0, 
        "start": 186.44790410995483, 
        "wavfile": "F002_002_01_0101"
    }
]