[
    {
        "index": 1, 
        "lyric": "It started off so well\n"
    }, 
    {
        "index": 2, 
        "lyric": "They said we made a perfect pair\n"
    }, 
    {
        "index": 3, 
        "lyric": "I clothed myself in your glory and your love\n"
    }, 
    {
        "index": 4, 
        "lyric": "How I loved you\n"
    }, 
    {
        "index": 5, 
        "lyric": "How I cried\n"
    }, 
    {
        "index": 6, 
        "lyric": "The years of care and loyalty\n"
    }, 
    {
        "index": 7, 
        "lyric": "Were nothing but a sham it seems\n"
    }, 
    {
        "index": 8, 
        "lyric": "The years belie we lived a lie\n"
    }, 
    {
        "index": 9, 
        "lyric": "I love you till I die\n"
    }, 
    {
        "index": 10, 
        "lyric": "Save me save me save me\n"
    }, 
    {
        "index": 11, 
        "lyric": "I can't face this life alone\n"
    }, 
    {
        "index": 12, 
        "lyric": "Save me save me save me\n"
    }, 
    {
        "index": 13, 
        "lyric": "I'm naked and I'm far from home\n"
    }, 
    {
        "index": 14, 
        "lyric": "The slate will soon be clean\n"
    }, 
    {
        "index": 15, 
        "lyric": "I'll erase the memories\n"
    }, 
    {
        "index": 16, 
        "lyric": "To start again with somebody new\n"
    }, 
    {
        "index": 17, 
        "lyric": "Was it all wasted\n"
    }, 
    {
        "index": 18, 
        "lyric": "All that love?\n"
    }, 
    {
        "index": 19, 
        "lyric": "I hang my head and I advertise\n"
    }, 
    {
        "index": 20, 
        "lyric": "A soul for sale or rent\n"
    }, 
    {
        "index": 21, 
        "lyric": "I have no heart I'm cold inside\n"
    }, 
    {
        "index": 22, 
        "lyric": "I have no real intent\n"
    }, 
    {
        "index": 23, 
        "lyric": "Save me save me save me\n"
    }, 
    {
        "index": 24, 
        "lyric": "I can't face this life alone\n"
    }, 
    {
        "index": 25, 
        "lyric": "Save me save me save me\n"
    }, 
    {
        "index": 26, 
        "lyric": "I'm naked and I'm far from home\n"
    }, 
    {
        "index": 27, 
        "lyric": "Each night I cry I still believe the lie\n"
    }, 
    {
        "index": 28, 
        "lyric": "I love you till I die\n"
    }, 
    {
        "index": 29, 
        "lyric": "Don't let me face my life alone\n"
    }, 
    {
        "index": 30, 
        "lyric": "Save me save me\n"
    }, 
    {
        "index": 31, 
        "lyric": "I'm naked and I'm far from home\n"
    }
]